suraida/__init__.py
suraida/gui.py
suraida/py.typed
suraida/version.py
suraida/widgets.py
suraida-1.0.0.dist-info/LICENSE.txt
suraida-1.0.0.dist-info/METADATA
suraida-1.0.0.dist-info/WHEEL
suraida-1.0.0.dist-info/top_level.txt
suraida-1.0.0.dist-info/RECORD
