Metadata-Version: 2.2
Name: suraida
Version: 1.0.0
Summary: Creates a simple GUI for interactive plotting with sliders
Author-email: Jens Koch <jens-koch@northwestern.edu>, Yunwei Lu <yunweilu2020@u.northwestern.edu>
License: BSD
Keywords: interactive,plotting
Platform: Linux
Platform: Mac OSX
Platform: Unix
Platform: Windows
Classifier: Development Status :: 5 - Production/Stable
Classifier: Intended Audience :: Science/Research
Classifier: License :: OSI Approved :: BSD License
Classifier: Programming Language :: Python
Classifier: Programming Language :: Python :: 3
Classifier: Topic :: Scientific/Engineering
Classifier: Operating System :: MacOS
Classifier: Operating System :: POSIX
Classifier: Operating System :: Unix
Classifier: Operating System :: Microsoft :: Windows
Requires-Python: >=3.10
License-File: LICENSE.txt
Requires-Dist: ipyvuetify
Requires-Dist: ipywidgets
Requires-Dist: traitlets
Requires-Dist: matplotlib
Requires-Dist: numpy
Requires-Dist: jupyter
